.foundryrc
.gitignore
.travis.yml
CHANGELOG.rst
MANIFEST.in
README.rst
UNLICENSE
release.sh
requirements-dev.txt
requirements.txt
setup.py
test.sh
test_linux.sh
sublime_info/SublimeInfo.py
sublime_info/__init__.py
sublime_info/errors.py
sublime_info.egg-info/PKG-INFO
sublime_info.egg-info/SOURCES.txt
sublime_info.egg-info/dependency_links.txt
sublime_info.egg-info/pbr.json
sublime_info.egg-info/requires.txt
sublime_info.egg-info/top_level.txt