Metadata-Version: 1.1
Name: sublime_info
Version: 0.2.0
Summary: Gather information about Sublime Text
Home-page: https://github.com/twolfson/sublime-info
Author: Todd Wolfson
Author-email: todd@twolfson.com
License: UNLICENSE
Download-URL: https://github.com/twolfson/sublime-info/archive/master.zip
Keywords: sublime,sublime text,info,plugin
Platform: UNKNOWN
Classifier: Development Status :: 3 - Alpha
Classifier: Intended Audience :: Developers
Classifier: License :: Public Domain
Classifier: Operating System :: OS Independent
Classifier: Programming Language :: Python
Classifier: Topic :: Text Editors
